bluer_agent/__init__.py
bluer_agent/__main__.py
bluer_agent/config.env
bluer_agent/env.py
bluer_agent/functions.py
bluer_agent/host.py
bluer_agent/logger.py
bluer_agent/sample.env
bluer_agent/urls.py
bluer_agent/.abcli/abcli.sh
bluer_agent/.abcli/actions.sh
bluer_agent/.abcli/alias.sh
bluer_agent/.abcli/audio.sh
bluer_agent/.abcli/bluer_agent.sh
bluer_agent/.abcli/chat.sh
bluer_agent/.abcli/crawl.sh
bluer_agent/.abcli/install.sh
bluer_agent/.abcli/rag.sh
bluer_agent/.abcli/transcribe.sh
bluer_agent/.abcli/voice.sh
bluer_agent/.abcli/audio/install.sh
bluer_agent/.abcli/audio/play.sh
bluer_agent/.abcli/audio/record.sh
bluer_agent/.abcli/audio/test.sh
bluer_agent/.abcli/chat/validate.sh
bluer_agent/.abcli/crawl/collect.sh
bluer_agent/.abcli/crawl/review.sh
bluer_agent/.abcli/rag/build_corpus.sh
bluer_agent/.abcli/rag/query.sh
bluer_agent/.abcli/tests/README.sh
bluer_agent/.abcli/tests/audio_play.sh
bluer_agent/.abcli/tests/audio_record.sh
bluer_agent/.abcli/tests/chat.sh
bluer_agent/.abcli/tests/crawl.sh
bluer_agent/.abcli/tests/crawl_all.sh
bluer_agent/.abcli/tests/help.sh
bluer_agent/.abcli/tests/rag_build_corpus.sh
bluer_agent/.abcli/tests/rag_query.sh
bluer_agent/.abcli/tests/transcription.sh
bluer_agent/.abcli/tests/version.sh
bluer_agent/.abcli/tests/voice.sh
bluer_agent/.abcli/voice/generate.sh
bluer_agent/README/__init__.py
bluer_agent/README/aliases.py
bluer_agent/README/audio.py
bluer_agent/README/build.py
bluer_agent/README/chat.py
bluer_agent/README/crawl.py
bluer_agent/README/docs.py
bluer_agent/README/rag.py
bluer_agent/README/transcription.py
bluer_agent/README/voice.py
bluer_agent/assets/review.html
bluer_agent/audio/__init__.py
bluer_agent/audio/__main__.py
bluer_agent/audio/env.py
bluer_agent/audio/play.py
bluer_agent/audio/properties.py
bluer_agent/audio/record.py
bluer_agent/chat/__init__.py
bluer_agent/chat/__main__.py
bluer_agent/chat/functions.py
bluer_agent/crawl/__init__.py
bluer_agent/crawl/__main__.py
bluer_agent/crawl/classes.py
bluer_agent-5.205.1.dist-info/licenses/LICENSE
bluer_agent-5.205.1.dist-info/METADATA
bluer_agent-5.205.1.dist-info/WHEEL
bluer_agent-5.205.1.dist-info/top_level.txt
bluer_agent-5.205.1.dist-info/RECORD
